geminpy/__init__.py
geminpy/__main__.py
geminpy/__version__.py
geminpy/api.py
geminpy/cli.py
geminpy/geminpy.py
geminpy/browser/__init__.py
geminpy/browser/automation.py
geminpy/browser/chrome.py
geminpy/browser/manager.py
geminpy/core/__init__.py
geminpy/core/config.py
geminpy/core/constants.py
geminpy/core/exceptions.py
geminpy/core/models.py
geminpy/gemini/__init__.py
geminpy/gemini/client.py
geminpy/gemini/executor.py
geminpy/gemini/parser.py
geminpy/utils/__init__.py
geminpy/utils/logging.py
geminpy/utils/platform.py
geminpy/utils/storage.py
geminpy-1.4.1.dist-info/METADATA
geminpy-1.4.1.dist-info/WHEEL
geminpy-1.4.1.dist-info/entry_points.txt
geminpy-1.4.1.dist-info/licenses/LICENSE
geminpy-1.4.1.dist-info/RECORD
